helper_dev_utils/.env.example_logger
helper_dev_utils/__init__.py
helper_dev_utils/helper_logger.py
helper_dev_utils/helper_pandas.py
helper_dev_utils/helper_utils_colab.py
helper_dev_utils/helper_utils_print.py
helper_dev_utils-0.5.3.dist-info/licenses/LICENSE
helper_dev_utils-0.5.3.dist-info/METADATA
helper_dev_utils-0.5.3.dist-info/WHEEL
helper_dev_utils-0.5.3.dist-info/top_level.txt
helper_dev_utils-0.5.3.dist-info/RECORD
