Metadata-Version: 2.4
Name: helper-dev-utils
Version: 0.5.3
Summary: Python 유틸리티 모음 라이브러리: 로깅, Pandas 확장, 출력, 경로 관리
Author-email: c0z0c <c0z0c.dev@gmail.com>
License: MIT
Project-URL: Homepage, https://github.com/c0z0c-helper/helper_dev_utils
Project-URL: Repository, https://github.com/c0z0c-helper/helper_dev_utils
Project-URL: Issues, https://github.com/c0z0c-helper/helper_dev_utils/issues
Keywords: utilities,logger,pandas,print,colab,jupyter,path,cache,google-drive,logging,visualization,tree,korean
Classifier: Development Status :: 4 - Beta
Classifier: Intended Audience :: Developers
Classifier: Intended Audience :: Science/Research
Classifier: Programming Language :: Python :: 3
Classifier: Programming Language :: Python :: 3.8
Classifier: Programming Language :: Python :: 3.9
Classifier: Programming Language :: Python :: 3.10
Classifier: Programming Language :: Python :: 3.11
Classifier: Programming Language :: Python :: 3.12
Classifier: Programming Language :: Python :: 3.13
Classifier: Topic :: Software Development :: Libraries :: Python Modules
Classifier: Topic :: Utilities
Requires-Python: >=3.8
License-File: LICENSE
Requires-Dist: matplotlib>=3.2.0
Requires-Dist: numpy>=1.16.0
Requires-Dist: pandas>=1.0.0
Requires-Dist: pytz>=2021.1; python_version < "3.9"
Provides-Extra: dev
Requires-Dist: pytest>=7.0.0; extra == "dev"
Requires-Dist: pytest-cov>=4.0.0; extra == "dev"
Requires-Dist: black>=23.0.0; extra == "dev"
Requires-Dist: ruff>=0.1.0; extra == "dev"
Provides-Extra: dotenv
Requires-Dist: python-dotenv>=0.19.0; extra == "dotenv"
Provides-Extra: jupyter
Requires-Dist: IPython>=7.0.0; extra == "jupyter"
Provides-Extra: torch
Requires-Dist: torch>=1.0.0; extra == "torch"
Provides-Extra: all
Requires-Dist: python-dotenv>=0.19.0; extra == "all"
Requires-Dist: IPython>=7.0.0; extra == "all"
Requires-Dist: torch>=1.0.0; extra == "all"
Dynamic: license-file
